LICENSE
README.md
setup.py
aliyun/__init__.py
aliyun/log/__init__.py
aliyun/log/acl_config.py
aliyun/log/acl_response.py
aliyun/log/async_sql_pb2.py
aliyun/log/async_sql_response.py
aliyun/log/auth.py
aliyun/log/common_response.py
aliyun/log/compress.py
aliyun/log/consumer_group_request.py
aliyun/log/consumer_group_response.py
aliyun/log/credentials.py
aliyun/log/cursor_response.py
aliyun/log/cursor_time_response.py
aliyun/log/delete_async_sql_request.py
aliyun/log/deletelogsrequest.py
aliyun/log/deletelogssresponse.py
aliyun/log/etl_config_response.py
aliyun/log/export_response.py
aliyun/log/external_store_config.py
aliyun/log/external_store_config_response.py
aliyun/log/get_async_sql_request.py
aliyun/log/getcontextlogsresponse.py
aliyun/log/getdeletelogsstatusrequest.py
aliyun/log/getdeletelogsstatusresponse.py
aliyun/log/gethistogramsrequest.py
aliyun/log/gethistogramsresponse.py
aliyun/log/getlogsrequest.py
aliyun/log/getlogsresponse.py
aliyun/log/histogram.py
aliyun/log/index_config.py
aliyun/log/index_config_response.py
aliyun/log/ingestion_response.py
aliyun/log/job.py
aliyun/log/listdeletelogsstasksrequest.py
aliyun/log/listdeletelogsstasksresponse.py
aliyun/log/listlogstoresrequest.py
aliyun/log/listlogstoresresponse.py
aliyun/log/listtopicsrequest.py
aliyun/log/listtopicsresponse.py
aliyun/log/log_logs_pb2.py
aliyun/log/log_logs_raw_pb2.py
aliyun/log/logclient.py
aliyun/log/logclient_core.py
aliyun/log/logclient_operator.py
aliyun/log/logexception.py
aliyun/log/logger_hanlder.py
aliyun/log/logitem.py
aliyun/log/logrequest.py
aliyun/log/logresponse.py
aliyun/log/logstore_config_response.py
aliyun/log/logtail_config_detail.py
aliyun/log/logtail_config_response.py
aliyun/log/logtail_pipeline_config_detail.py
aliyun/log/logtail_pipeline_config_response.py
aliyun/log/machine_group_detail.py
aliyun/log/machinegroup_response.py
aliyun/log/metering_mode_response.py
aliyun/log/multimodal_config_response.py
aliyun/log/object_response.py
aliyun/log/odps_sink.py
aliyun_log_python_sdk.egg-info/PKG-INFO
aliyun_log_python_sdk.egg-info/SOURCES.txt
aliyun_log_python_sdk.egg-info/dependency_links.txt
aliyun_log_python_sdk.egg-info/requires.txt
aliyun_log_python_sdk.egg-info/top_level.txt
